annorepo/__init__.py
annorepo/client.py
annorepo/grpc/__init__.py
annorepo/grpc/annotation_upload_service_pb2.py
annorepo/grpc/annotation_upload_service_pb2.pyi
annorepo/grpc/annotation_upload_service_pb2_grpc.py
annorepo/grpc/hello_service_pb2.py
annorepo/grpc/hello_service_pb2.pyi
annorepo/grpc/hello_service_pb2_grpc.py
annorepo/model.py
annorepo_client-0.3.2.dist-info/AUTHORS
annorepo_client-0.3.2.dist-info/LICENSE
annorepo_client-0.3.2.dist-info/METADATA
annorepo_client-0.3.2.dist-info/WHEEL
annorepo_client-0.3.2.dist-info/entry_points.txt
annorepo_client-0.3.2.dist-info/RECORD
