Metadata-Version: 2.3
Name: annorepo-client
Version: 0.3.2
Summary: A Python client for accessing an AnnoRepo server
License: MIT
Author: Bram Buitendijk
Author-email: bram.buitendijk@di.huc.knaw.nl
Requires-Python: >=3.8,<4.0
Classifier: Development Status :: 4 - Beta
Classifier: Intended Audience :: Developers
Classifier: License :: OSI Approved :: MIT License
Classifier: Operating System :: OS Independent
Classifier: Programming Language :: Python :: 3
Classifier: Programming Language :: Python :: 3.8
Classifier: Programming Language :: Python :: 3.9
Classifier: Programming Language :: Python :: 3.10
Classifier: Programming Language :: Python :: 3.11
Classifier: Programming Language :: Python :: 3.12
Classifier: Programming Language :: Python :: 3.13
Requires-Dist: colorama (>=0.4.4,<0.5.0)
Requires-Dist: google (>=3.0.0,<4.0.0)
Requires-Dist: google-api-python-client (>=2.103.0,<3.0.0)
Requires-Dist: icecream (>=2.1.2,<3.0.0)
Requires-Dist: requests (==2.32.3)
Requires-Dist: retry2 (>=0.9.5,<0.10.0)
Requires-Dist: sphinx-rtd-theme (>=2.0.0,<3.0.0)
Requires-Dist: tabulate (>=0.9.0,<0.10.0)
Project-URL: Bug Tracker, https://github.com/knaw-huc/annorepo-python-client/issues
Project-URL: Homepage, https://github.com/knaw-huc/annorepo-python-client
Project-URL: Repository, https://github.com/knaw-huc/annorepo-python-client
